dddmisc_mongo_uow/__init__.py
dddmisc_mongo_uow/abstraction.py
dddmisc_mongo_uow/unit_of_work_tools.py
dddmisc_mongo_uow-1.0.1.dist-info/WHEEL
dddmisc_mongo_uow-1.0.1.dist-info/METADATA
dddmisc_mongo_uow-1.0.1.dist-info/RECORD
