Metadata-Version: 2.1
Name: dddmisc-mongo-uow
Version: 1.0.1
Summary: 
Author: Aziz
Author-email: walkingonadream2012@mail.ru
Requires-Python: >=3.10,<4.0
Classifier: Programming Language :: Python :: 3
Classifier: Programming Language :: Python :: 3.10
Classifier: Programming Language :: Python :: 3.11
Requires-Dist: ddd-misc (>=0.8.1,<0.9.0)
Requires-Dist: motor (>=3.0.0,<4.0.0)
